{"JFY0hgaG0S/iU2n0737t4A==":"olympus%2003%2009%20wr%20umbau_0171b&w-1460x1947.png","uoxuLWL7HyTSM+EEt2b1JQ==":"olympus%2003%2009%20wr%20umbau_0148b&w-2000x1500.png","sT80Y4RCGNBrSInGgrjIuA==":"background3.jpg","Ur1h2vqduilwoqtv40BKUg==":"yoga-d%C3%BCsseldorf-1137x1134.png","/zBkTjmdEv8SRwFlHwirzA==":"yoga-d%C3%BCsseldorf-1137x1134.png","SWgbMsVZiXI2WEGKzJpHzg==":"yoga-d%C3%BCsseldorf-1137x1134.png","6XooufGyOrEYCpjK9JobTw==":"yoga-d%C3%BCsseldorf-1137x1134.png","j8wi/weRBB1L3qwF/f/6Xg==":"yoga-d%C3%BCsseldorf-1137x1134.png","Dc42n1m5vXh9XuvkyuoxDQ==":"yoga-d%C3%BCsseldorf-1137x1134.png","O2ZEDXD+LpJVN6QGjYo7mw==":"yoga-d%C3%BCsseldorf-1137x1134.png","Gr/I11A/7mHoMt05dP6mhg==":"yoga%20f%C3%BCr%20zu%20hause%201-700x467.png","/j/UyPzHUNWPj/6jcgABPg==":"yoga%20fuer%20zu%20hause%201-700x467.png","4SY8s5MHtE+Q/+sZPHbPcQ==":"weltenraum-logo-ps-1-500x102.png","78JPSS0w8geouOMSulBOTw==":"assana-1%20min-270x270.png","liBiGb5u8T/f4vJjasORRw==":"spirale%20min-352x352.png","lm9oCpIUubPmKQ0jl7Rsjw==":"integrationsarbeit%20min-261x260.png","LFzpaERk7343x1MCzyOqjQ==":"weltenraum-logo-ps-2-500x102.png","N1iF5mgKzOmhDy3vDisHtw==":"weltenraum-2%20xmin-790x417.png","BikXScCYKNOjeKiC4F18aQ==":"weltenraum-2%20xmin-790x417.png","30jq0thXHjL27smxcYw1CQ==":"yogareise-2%20min-352x235.png","24q6Y5rSB/zq0jY/0KdUhw==":"assana-2%20min-359x178.png","LTnlyyh+yL3EUn/aygmghA==":"meditation%20min-382x210.png","e+P5yCaL4YMzMt1sNjZPpg==":"yoga%20fuer%20zu%20hause%20min-380x188.png","7RiDn+HvGtVyUhZnqXmTpA==":"yoga%20fuer%20zu%20hause%20min-380x188.png","7GWxJWGLa8CQOO0L1PAtPw==":"insel-2%20xmin-378x218.png","qo6Niju7nWy4hCcwqXOE2A==":"integrationsarbeit%20min-261x260.png","51ptYcpzElsdhua12BqsKA==":"seminarraum-2%20xmin-363x363.png","OeottE0msP6kQTJmTOOvsg==":"vermietung%20min-364x364.png","COSjO3E+rDdzVmhEFBjYgw==":"duesseldorf%20min-363x356.png","s09DZUEUIAj2limn7srtYg==":"vita-3%20xxmin-1445x1000.png","fcJez9m6G5vamXy21jim+A==":"vita-3%20xxmin-1445x1000.png","vnHyzNNP9dlgTa9f/Mxq8Q==":"vita-3%20xxmin-1445x1000.png","2u22oEKW9U/ZDZMVv7UqCw==":"vita-3%20xxmin-1445x1000.png","ZWxIwH+wFIu7ubtLo9AiuA==":"anhang%20min-168x126.png","pa5Dkwo/T1qgW/t0h+fQvA==":"background5-1.jpg","OL7wf4luB3yfBk8puVtHxw==":"yogareise-2%20min-352x235.png","nR5dtOQyaEPcj6+ZEro+1w==":"yogareise-2%20min-352x235.png","tcfvUsfibKdPzvtzw2ZTDw==":"kreatives%20denken%202-382x210.png","p2ayd6wR0C2rhjvK29cXmQ==":"kreatives-denken-2-382x210.png","w5itMhJmZjWU31+6sUBWqQ==":"kundalini%20meditation-382x210.png","9GoCFKmN7jaGfjO/cZLXBg==":"vermietung%20min-364x364.png","L4Wb4C8Kk/ixdnyPq3MRiQ==":"seminarraum-2%20xmin-363x363.png","l+eCAubYz3BJhQ79xhc6Xw==":"seminarraum-2%20xmin-363x363.png","b1yfs+0amv8g8N+i9B/t4A==":"053-lumixg8-p1020289.jpeg","NsCVM+QCZGyZYAxHKeC5mA==":"051-lumixg8-p1020287.jpeg","HcyFW4/GTlsWxb/d+D+Fow==":"082-lumixg8-p1020322.jpeg","BhN6PyHyfxgTScccGMjX8Q==":"070-lumixg8-p1020307.jpeg","NTfZ2DdUZA8Xj7Y9cJ6Mkg==":"070-lumixg8-p1020307.jpg","wRDJeI/+66CTEO2gS9L0pg==":"083-lumixg8-p1020323.jpeg","U5xKCvaDBNkipU3ysj0VjA==":"118%20-%20lumixg8%20p1020288-30-663x284.png","Di6BP9k965CVInOF/wWBeg==":"118%20-%20lumixg8%20p1020288-30-663x284.png","CV3/4KbQwxIa+JDAhIn7Rg==":"118%20-%20lumixg8%20p1020288-2000x856.jpg","R0Qoqks8oD1WekektzHyng==":"118%20-%20lumixg8%20p1020288-2000x856.jpeg","iNMfbs8MqxDE9/C6E77eUA==":"118-lumixg8-p1020288-30-663x284.png","l8teUuE/HGuZYXoTlv0RzQ==":"yogaraum-1-2000x966.jpg","hjA14Uk6cvKpD/GYXz3RtQ==":"yogaraum-1-2000x966.jpeg","RN6PgHG0rIegB1pM92ExKA==":"06.jpg","rYYy3AJ2SZXF+uuRmuBjZQ==":"118-lumixg8-p1020288-31-663x284.png","RcBE3Osc8/i7hrAKPrGPgA==":"050%20-%20lumixg8%20p1020286-2000x1500.jpg","2w4Iy1s9ZB8uz731clFeZw==":"049%20-%20lumixg8%20p1020285-2000x1500.jpg","qYZ23Oq/GIGH/C5pt+spMw==":"049-lumixg8-p1020285-800x600.jpeg","uQ5Rlp/9KL+mr2fL9togcg==":"053%20-%20lumixg8%20p1020289-2000x1500.jpg","O+eMHXBOnruJeA5mOpDoYA==":"050%20-%20lumixg8%20p1020286-2000x1500.jpeg","2WJ1v/Nnwj5/ufy6QjHMhA==":"118-lumixg8-p1020288-32-663x284.png","OgipsJcTdflKPqN9jlASKg==":"118%20-%20lumixg8%20p1020288-2000x856.jpeg","zSIyrjrEUF5L+pGNE1zZzw==":"052%20-%20lumixg8%20p1020288-2000x784.jpg","upf+PaW++UuCItLabhbWWQ==":"052%20-%20lumixg8%20p1020288-2000x784.jpeg","rfmk4YLSrcq4cJW2nc+Mxg==":"053-lumixg8-p1020289-1.jpeg","Fdi898RWFaUbyLZHT84V2w==":"118-lumixg8-p1020288-800x342.jpeg","WIoDblUJRsdrclaxKCe7nw==":"046%20-%20lumixg8%20p1020282-1046x418.jpeg","PkEjdF9uEUhBi6UyH/54cA==":"005%20-%20lumixg8%20p1020294-2000x1500.png","REozoUXMFltyhLU2KpkDYQ==":"005%20-%20lumixg8%20p1020294-2000x1500.png","soabLdpgSltBDZRXrTy4uw==":"005%20-%20lumixg8%20p1020294%20(5000)-432x324.png","6cl+ThKayMGGfDSeRer9HA==":"005%20-%20lumixg8%20p1020294-500-432x324.png","HhwHD9d0phUV/jrif6BKwQ==":"005%20-%20lumixg8%20p1020294-500-432x324.png","eDfHYGhpzI/kH+51xGXF9w==":"005%20-%20lumixg8%20p1020294-20-518x389.jpg","1PrjOuiIj16fAUU56mjQRQ==":"009%20-%20lumixg8%20p1020310-2000x1500.png","5vTLRsTDnRxjaYQyPOMlQw==":"009%20-%20lumixg8%20p1020310-2000x1500.png","Owwa5UJK37gdtt9E/60/hQ==":"011%20-%20lumixg8%20p1020318-2000x1500.png","wgW6VtfbwY/TV8LlLWRPjg==":"011%20-%20lumixg8%20p1020318-2000x1500.png","+2e5byi7dcazChX6m6ERSw==":"013%20-%20lumixg8%20p1020323-2000x1500.png","6yn3EAnM6+ODXQ17Grw63g==":"002%20-%20lumixg8%20p1020288-2000x886.png","AAZUF9xBSuG0WeburVU5jA==":"013%20-%20lumixg8%20p1020323-2000x1500.png","Xq2XQspsbwd2aIDbm0Vyug==":"002%20-%20lumixg8%20p1020288-2000x886.png","DUGpeeaV8t4Nh9lUA4GHfw==":"014%20-%20lumixg8%20p1020330-2000x1500.png","LDDW9lCzFllRn7YLLk6GUg==":"014%20-%20lumixg8%20p1020330-2000x1500.png","S/v6rYIugTiD2pvG5oGIQQ==":"016%20-%20lumixg8%20p1020345-2000x886.png","wJxvgOnRfnMDfFLqHK67zw==":"016%20-%20lumixg8%20p1020345-2000x886.png","D2JL/OMSGgpgvNFVxyqD/A==":"002%20-%20lumixg8%20p1020288-2000x886.png","z86OuWEDsCwD6UAKrFSjpQ==":"015%20-%20lumixg8%20p1020337-2000x886.png"}